dolus.py
dolus-0.1.2.dist-info/entry_points.txt
dolus-0.1.2.dist-info/LICENSE.md
dolus-0.1.2.dist-info/WHEEL
dolus-0.1.2.dist-info/METADATA
dolus-0.1.2.dist-info/RECORD
