Metadata-Version: 2.1
Name: dolus
Version: 0.1.2
Summary: A command-line interface to put effects on your virtual camera(OBS/Unity/v4l2loopback)
Home-page: https://github.com/AvanindraC/dolus
License: MIT
Author: Avanindra Chakraborty
Requires-Python: >=3.7,<4.0
Classifier: License :: OSI Approved :: MIT License
Classifier: Operating System :: OS Independent
Classifier: Programming Language :: Python :: 3
Classifier: Programming Language :: Python :: 3.6
Classifier: Programming Language :: Python :: 3.7
Classifier: Programming Language :: Python :: 3.8
Classifier: Programming Language :: Python :: 3.9
Requires-Dist: click (>=8.0.1,<9.0.0)
Requires-Dist: click-help-colors (>=0.9.1,<0.10.0)
Requires-Dist: numpy (>=1.21.2,<2.0.0)
Requires-Dist: opencv-python (>=4.5.3,<5.0.0)
Requires-Dist: pafy (>=0.5.5,<0.6.0)
Requires-Dist: pyvirtualcam (>=0.8.0,<0.9.0)
Requires-Dist: requests (>=2.26.0,<3.0.0)
Requires-Dist: youtube_dl (>=2021.6.6,<2022.0.0)
Project-URL: Repository, https://github.com/AvanindraC/dolus
